<?xml version="1.0" encoding="UTF-8"?>
<SharedInstrument><Metadata type="crf"><Field><FieldName>csqr_q1</FieldName><FormName>coping_strategies_questionnaire_revised</FormName><FormMenuDescription>Coping Strategies Questionnaire Revised</FormMenuDescription><FieldOrder>3</FieldOrder><ElementPreceedingHeader>Directions: Please read each response to low back pain below and fill in the circle on how often you respond that way when dealing with your low back pain.</ElementPreceedingHeader><ElementType>radio</ElementType><ElementLabel>1. I try to feel distant from the pain, almost as if the pain was in someone else's body.</ElementLabel><ElementEnum><RawValue>0, Never do that \n 1, Very rarely do that \n 2, Rarely do that \n 3, Sometimes do that \n 4, Often do that \n 5, Usually do that \n 6, Always do that</RawValue><StructuredValue><Value value="0">Never do that</Value><Value value="1">Very rarely do that</Value><Value value="2">Rarely do that</Value><Value value="3">Sometimes do that</Value><Value value="4">Often do that</Value><Value value="5">Usually do that</Value><Value value="6">Always do that</Value></StructuredValue></ElementEnum><FieldReq>0</FieldReq><MatrixGroupName>pain_scale</MatrixGroupName><MatrixRanking>0</MatrixRanking></Field><Field><FieldName>csqr_q2</FieldName><FormName>coping_strategies_questionnaire_revised</FormName><FieldOrder>4</FieldOrder><ElementType>radio</ElementType><ElementLabel>2. I try to think of something pleasant.</ElementLabel><ElementEnum><RawValue>0, Never do that \n 1, Very rarely do that \n 2, Rarely do that \n 3, Sometimes do that \n 4, Often do that \n 5, Usually do that \n 6, Always do that</RawValue><StructuredValue><Value value="0">Never do that</Value><Value value="1">Very rarely do that</Value><Value value="2">Rarely do that</Value><Value value="3">Sometimes do that</Value><Value value="4">Often do that</Value><Value value="5">Usually do that</Value><Value value="6">Always do that</Value></StructuredValue></ElementEnum><FieldReq>0</FieldReq><MatrixGroupName>pain_scale</MatrixGroupName><MatrixRanking>0</MatrixRanking></Field><Field><FieldName>csqr_q3</FieldName><FormName>coping_strategies_questionnaire_revised</FormName><FieldOrder>5</FieldOrder><ElementType>radio</ElementType><ElementLabel>3. It's terrible and I feel it's never going to get any better.</ElementLabel><ElementEnum><RawValue>0, Never do that \n 1, Very rarely do that \n 2, Rarely do that \n 3, Sometimes do that \n 4, Often do that \n 5, Usually do that \n 6, Always do that</RawValue><StructuredValue><Value value="0">Never do that</Value><Value value="1">Very rarely do that</Value><Value value="2">Rarely do that</Value><Value value="3">Sometimes do that</Value><Value value="4">Often do that</Value><Value value="5">Usually do that</Value><Value value="6">Always do that</Value></StructuredValue></ElementEnum><FieldReq>0</FieldReq><MatrixGroupName>pain_scale</MatrixGroupName><MatrixRanking>0</MatrixRanking></Field><Field><FieldName>csqr_q4</FieldName><FormName>coping_strategies_questionnaire_revised</FormName><FieldOrder>6</FieldOrder><ElementType>radio</ElementType><ElementLabel>4. I tell myself to be brave and carry on despite the pain.</ElementLabel><ElementEnum><RawValue>0, Never do that \n 1, Very rarely do that \n 2, Rarely do that \n 3, Sometimes do that \n 4, Often do that \n 5, Usually do that \n 6, Always do that</RawValue><StructuredValue><Value value="0">Never do that</Value><Value value="1">Very rarely do that</Value><Value value="2">Rarely do that</Value><Value value="3">Sometimes do that</Value><Value value="4">Often do that</Value><Value value="5">Usually do that</Value><Value value="6">Always do that</Value></StructuredValue></ElementEnum><FieldReq>0</FieldReq><MatrixGroupName>pain_scale</MatrixGroupName><MatrixRanking>0</MatrixRanking></Field><Field><FieldName>csqr_q5</FieldName><FormName>coping_strategies_questionnaire_revised</FormName><FieldOrder>7</FieldOrder><ElementType>radio</ElementType><ElementLabel>5. I tell myself that I can overcome the pain.</ElementLabel><ElementEnum><RawValue>0, Never do that \n 1, Very rarely do that \n 2, Rarely do that \n 3, Sometimes do that \n 4, Often do that \n 5, Usually do that \n 6, Always do that</RawValue><StructuredValue><Value value="0">Never do that</Value><Value value="1">Very rarely do that</Value><Value value="2">Rarely do that</Value><Value value="3">Sometimes do that</Value><Value value="4">Often do that</Value><Value value="5">Usually do that</Value><Value value="6">Always do that</Value></StructuredValue></ElementEnum><FieldReq>0</FieldReq><MatrixGroupName>pain_scale</MatrixGroupName><MatrixRanking>0</MatrixRanking></Field><Field><FieldName>csqr_q6</FieldName><FormName>coping_strategies_questionnaire_revised</FormName><FieldOrder>8</FieldOrder><ElementType>radio</ElementType><ElementLabel>6. It's awful and I feel that it overwhelms me.</ElementLabel><ElementEnum><RawValue>0, Never do that \n 1, Very rarely do that \n 2, Rarely do that \n 3, Sometimes do that \n 4, Often do that \n 5, Usually do that \n 6, Always do that</RawValue><StructuredValue><Value value="0">Never do that</Value><Value value="1">Very rarely do that</Value><Value value="2">Rarely do that</Value><Value value="3">Sometimes do that</Value><Value value="4">Often do that</Value><Value value="5">Usually do that</Value><Value value="6">Always do that</Value></StructuredValue></ElementEnum><FieldReq>0</FieldReq><MatrixGroupName>pain_scale</MatrixGroupName><MatrixRanking>0</MatrixRanking></Field><Field><FieldName>csqr_q7</FieldName><FormName>coping_strategies_questionnaire_revised</FormName><FieldOrder>9</FieldOrder><ElementType>radio</ElementType><ElementLabel>7. I feel my life isn't worth living.</ElementLabel><ElementEnum><RawValue>0, Never do that \n 1, Very rarely do that \n 2, Rarely do that \n 3, Sometimes do that \n 4, Often do that \n 5, Usually do that \n 6, Always do that</RawValue><StructuredValue><Value value="0">Never do that</Value><Value value="1">Very rarely do that</Value><Value value="2">Rarely do that</Value><Value value="3">Sometimes do that</Value><Value value="4">Often do that</Value><Value value="5">Usually do that</Value><Value value="6">Always do that</Value></StructuredValue></ElementEnum><FieldReq>0</FieldReq><MatrixGroupName>pain_scale</MatrixGroupName><MatrixRanking>0</MatrixRanking></Field><Field><FieldName>csqr_q8</FieldName><FormName>coping_strategies_questionnaire_revised</FormName><FieldOrder>10</FieldOrder><ElementType>radio</ElementType><ElementLabel>8. I pray to God it won't last long.</ElementLabel><ElementEnum><RawValue>0, Never do that \n 1, Very rarely do that \n 2, Rarely do that \n 3, Sometimes do that \n 4, Often do that \n 5, Usually do that \n 6, Always do that</RawValue><StructuredValue><Value value="0">Never do that</Value><Value value="1">Very rarely do that</Value><Value value="2">Rarely do that</Value><Value value="3">Sometimes do that</Value><Value value="4">Often do that</Value><Value value="5">Usually do that</Value><Value value="6">Always do that</Value></StructuredValue></ElementEnum><FieldReq>0</FieldReq><MatrixGroupName>pain_scale</MatrixGroupName><MatrixRanking>0</MatrixRanking></Field><Field><FieldName>csqr_q9</FieldName><FormName>coping_strategies_questionnaire_revised</FormName><FieldOrder>11</FieldOrder><ElementType>radio</ElementType><ElementLabel>9. I try not to think of it as my body, but rather as something separate from me.</ElementLabel><ElementEnum><RawValue>0, Never do that \n 1, Very rarely do that \n 2, Rarely do that \n 3, Sometimes do that \n 4, Often do that \n 5, Usually do that \n 6, Always do that</RawValue><StructuredValue><Value value="0">Never do that</Value><Value value="1">Very rarely do that</Value><Value value="2">Rarely do that</Value><Value value="3">Sometimes do that</Value><Value value="4">Often do that</Value><Value value="5">Usually do that</Value><Value value="6">Always do that</Value></StructuredValue></ElementEnum><FieldReq>0</FieldReq><MatrixGroupName>pain_scale</MatrixGroupName><MatrixRanking>0</MatrixRanking></Field><Field><FieldName>csqr_q10</FieldName><FormName>coping_strategies_questionnaire_revised</FormName><FieldOrder>12</FieldOrder><ElementType>radio</ElementType><ElementLabel>10. I don't think about the pain.</ElementLabel><ElementEnum><RawValue>0, Never do that \n 1, Very rarely do that \n 2, Rarely do that \n 3, Sometimes do that \n 4, Often do that \n 5, Usually do that \n 6, Always do that</RawValue><StructuredValue><Value value="0">Never do that</Value><Value value="1">Very rarely do that</Value><Value value="2">Rarely do that</Value><Value value="3">Sometimes do that</Value><Value value="4">Often do that</Value><Value value="5">Usually do that</Value><Value value="6">Always do that</Value></StructuredValue></ElementEnum><FieldReq>0</FieldReq><MatrixGroupName>pain_scale</MatrixGroupName><MatrixRanking>0</MatrixRanking></Field><Field><FieldName>csqr_q11</FieldName><FormName>coping_strategies_questionnaire_revised</FormName><FieldOrder>13</FieldOrder><ElementType>radio</ElementType><ElementLabel>11. I tell myself I can't let the pain stand in the way of what I have to do.</ElementLabel><ElementEnum><RawValue>0, Never do that \n 1, Very rarely do that \n 2, Rarely do that \n 3, Sometimes do that \n 4, Often do that \n 5, Usually do that \n 6, Always do that</RawValue><StructuredValue><Value value="0">Never do that</Value><Value value="1">Very rarely do that</Value><Value value="2">Rarely do that</Value><Value value="3">Sometimes do that</Value><Value value="4">Often do that</Value><Value value="5">Usually do that</Value><Value value="6">Always do that</Value></StructuredValue></ElementEnum><FieldReq>0</FieldReq><MatrixGroupName>pain_scale</MatrixGroupName><MatrixRanking>0</MatrixRanking></Field><Field><FieldName>csqr_q12</FieldName><FormName>coping_strategies_questionnaire_revised</FormName><FieldOrder>14</FieldOrder><ElementType>radio</ElementType><ElementLabel>12. I don't pay any attention to it.</ElementLabel><ElementEnum><RawValue>0, Never do that \n 1, Very rarely do that \n 2, Rarely do that \n 3, Sometimes do that \n 4, Often do that \n 5, Usually do that \n 6, Always do that</RawValue><StructuredValue><Value value="0">Never do that</Value><Value value="1">Very rarely do that</Value><Value value="2">Rarely do that</Value><Value value="3">Sometimes do that</Value><Value value="4">Often do that</Value><Value value="5">Usually do that</Value><Value value="6">Always do that</Value></StructuredValue></ElementEnum><FieldReq>0</FieldReq><MatrixGroupName>pain_scale</MatrixGroupName><MatrixRanking>0</MatrixRanking></Field><Field><FieldName>csqr_q13</FieldName><FormName>coping_strategies_questionnaire_revised</FormName><FieldOrder>15</FieldOrder><ElementType>radio</ElementType><ElementLabel>13. I pretend it's not there.</ElementLabel><ElementEnum><RawValue>0, Never do that \n 1, Very rarely do that \n 2, Rarely do that \n 3, Sometimes do that \n 4, Often do that \n 5, Usually do that \n 6, Always do that</RawValue><StructuredValue><Value value="0">Never do that</Value><Value value="1">Very rarely do that</Value><Value value="2">Rarely do that</Value><Value value="3">Sometimes do that</Value><Value value="4">Often do that</Value><Value value="5">Usually do that</Value><Value value="6">Always do that</Value></StructuredValue></ElementEnum><FieldReq>0</FieldReq><MatrixGroupName>pain_scale</MatrixGroupName><MatrixRanking>0</MatrixRanking></Field><Field><FieldName>csqr_q14</FieldName><FormName>coping_strategies_questionnaire_revised</FormName><FieldOrder>16</FieldOrder><ElementType>radio</ElementType><ElementLabel>14. I worry all the time about whether it will end.</ElementLabel><ElementEnum><RawValue>0, Never do that \n 1, Very rarely do that \n 2, Rarely do that \n 3, Sometimes do that \n 4, Often do that \n 5, Usually do that \n 6, Always do that</RawValue><StructuredValue><Value value="0">Never do that</Value><Value value="1">Very rarely do that</Value><Value value="2">Rarely do that</Value><Value value="3">Sometimes do that</Value><Value value="4">Often do that</Value><Value value="5">Usually do that</Value><Value value="6">Always do that</Value></StructuredValue></ElementEnum><FieldReq>0</FieldReq><MatrixGroupName>pain_scale</MatrixGroupName><MatrixRanking>0</MatrixRanking></Field><Field><FieldName>csqr_q15</FieldName><FormName>coping_strategies_questionnaire_revised</FormName><FieldOrder>17</FieldOrder><ElementType>radio</ElementType><ElementLabel>15. I replay in my mind pleasant experiences in the past.</ElementLabel><ElementEnum><RawValue>0, Never do that \n 1, Very rarely do that \n 2, Rarely do that \n 3, Sometimes do that \n 4, Often do that \n 5, Usually do that \n 6, Always do that</RawValue><StructuredValue><Value value="0">Never do that</Value><Value value="1">Very rarely do that</Value><Value value="2">Rarely do that</Value><Value value="3">Sometimes do that</Value><Value value="4">Often do that</Value><Value value="5">Usually do that</Value><Value value="6">Always do that</Value></StructuredValue></ElementEnum><FieldReq>0</FieldReq><MatrixGroupName>pain_scale</MatrixGroupName><MatrixRanking>0</MatrixRanking></Field><Field><FieldName>csqr_q16</FieldName><FormName>coping_strategies_questionnaire_revised</FormName><FieldOrder>18</FieldOrder><ElementType>radio</ElementType><ElementLabel>16. I think of people I enjoy doing things with.</ElementLabel><ElementEnum><RawValue>0, Never do that \n 1, Very rarely do that \n 2, Rarely do that \n 3, Sometimes do that \n 4, Often do that \n 5, Usually do that \n 6, Always do that</RawValue><StructuredValue><Value value="0">Never do that</Value><Value value="1">Very rarely do that</Value><Value value="2">Rarely do that</Value><Value value="3">Sometimes do that</Value><Value value="4">Often do that</Value><Value value="5">Usually do that</Value><Value value="6">Always do that</Value></StructuredValue></ElementEnum><FieldReq>0</FieldReq><MatrixGroupName>pain_scale</MatrixGroupName><MatrixRanking>0</MatrixRanking></Field><Field><FieldName>csqr_q17</FieldName><FormName>coping_strategies_questionnaire_revised</FormName><FieldOrder>19</FieldOrder><ElementType>radio</ElementType><ElementLabel>17. I pray for the pain to stop.</ElementLabel><ElementEnum><RawValue>0, Never do that \n 1, Very rarely do that \n 2, Rarely do that \n 3, Sometimes do that \n 4, Often do that \n 5, Usually do that \n 6, Always do that</RawValue><StructuredValue><Value value="0">Never do that</Value><Value value="1">Very rarely do that</Value><Value value="2">Rarely do that</Value><Value value="3">Sometimes do that</Value><Value value="4">Often do that</Value><Value value="5">Usually do that</Value><Value value="6">Always do that</Value></StructuredValue></ElementEnum><FieldReq>0</FieldReq><MatrixGroupName>pain_scale</MatrixGroupName><MatrixRanking>0</MatrixRanking></Field><Field><FieldName>csqr_q18</FieldName><FormName>coping_strategies_questionnaire_revised</FormName><FieldOrder>20</FieldOrder><ElementType>radio</ElementType><ElementLabel>18. I imagine that the pain is outside of my body.</ElementLabel><ElementEnum><RawValue>0, Never do that \n 1, Very rarely do that \n 2, Rarely do that \n 3, Sometimes do that \n 4, Often do that \n 5, Usually do that \n 6, Always do that</RawValue><StructuredValue><Value value="0">Never do that</Value><Value value="1">Very rarely do that</Value><Value value="2">Rarely do that</Value><Value value="3">Sometimes do that</Value><Value value="4">Often do that</Value><Value value="5">Usually do that</Value><Value value="6">Always do that</Value></StructuredValue></ElementEnum><FieldReq>0</FieldReq><MatrixGroupName>pain_scale</MatrixGroupName><MatrixRanking>0</MatrixRanking></Field><Field><FieldName>csqr_q19</FieldName><FormName>coping_strategies_questionnaire_revised</FormName><FieldOrder>21</FieldOrder><ElementType>radio</ElementType><ElementLabel>19. I just go on as if nothing happened.</ElementLabel><ElementEnum><RawValue>0, Never do that \n 1, Very rarely do that \n 2, Rarely do that \n 3, Sometimes do that \n 4, Often do that \n 5, Usually do that \n 6, Always do that</RawValue><StructuredValue><Value value="0">Never do that</Value><Value value="1">Very rarely do that</Value><Value value="2">Rarely do that</Value><Value value="3">Sometimes do that</Value><Value value="4">Often do that</Value><Value value="5">Usually do that</Value><Value value="6">Always do that</Value></StructuredValue></ElementEnum><FieldReq>0</FieldReq><MatrixGroupName>pain_scale</MatrixGroupName><MatrixRanking>0</MatrixRanking></Field><Field><FieldName>csqr_q20</FieldName><FormName>coping_strategies_questionnaire_revised</FormName><FieldOrder>22</FieldOrder><ElementType>radio</ElementType><ElementLabel>20. Although it hurts, I just keep on going.</ElementLabel><ElementEnum><RawValue>0, Never do that \n 1, Very rarely do that \n 2, Rarely do that \n 3, Sometimes do that \n 4, Often do that \n 5, Usually do that \n 6, Always do that</RawValue><StructuredValue><Value value="0">Never do that</Value><Value value="1">Very rarely do that</Value><Value value="2">Rarely do that</Value><Value value="3">Sometimes do that</Value><Value value="4">Often do that</Value><Value value="5">Usually do that</Value><Value value="6">Always do that</Value></StructuredValue></ElementEnum><FieldReq>0</FieldReq><MatrixGroupName>pain_scale</MatrixGroupName><MatrixRanking>0</MatrixRanking></Field><Field><FieldName>csqr_q21</FieldName><FormName>coping_strategies_questionnaire_revised</FormName><FieldOrder>23</FieldOrder><ElementType>radio</ElementType><ElementLabel>21. I feel I can't stand it anymore.</ElementLabel><ElementEnum><RawValue>0, Never do that \n 1, Very rarely do that \n 2, Rarely do that \n 3, Sometimes do that \n 4, Often do that \n 5, Usually do that \n 6, Always do that</RawValue><StructuredValue><Value value="0">Never do that</Value><Value value="1">Very rarely do that</Value><Value value="2">Rarely do that</Value><Value value="3">Sometimes do that</Value><Value value="4">Often do that</Value><Value value="5">Usually do that</Value><Value value="6">Always do that</Value></StructuredValue></ElementEnum><FieldReq>0</FieldReq><MatrixGroupName>pain_scale</MatrixGroupName><MatrixRanking>0</MatrixRanking></Field><Field><FieldName>csqr_q22</FieldName><FormName>coping_strategies_questionnaire_revised</FormName><FieldOrder>24</FieldOrder><ElementType>radio</ElementType><ElementLabel>22. I ignore it.</ElementLabel><ElementEnum><RawValue>0, Never do that \n 1, Very rarely do that \n 2, Rarely do that \n 3, Sometimes do that \n 4, Often do that \n 5, Usually do that \n 6, Always do that</RawValue><StructuredValue><Value value="0">Never do that</Value><Value value="1">Very rarely do that</Value><Value value="2">Rarely do that</Value><Value value="3">Sometimes do that</Value><Value value="4">Often do that</Value><Value value="5">Usually do that</Value><Value value="6">Always do that</Value></StructuredValue></ElementEnum><FieldReq>0</FieldReq><MatrixGroupName>pain_scale</MatrixGroupName><MatrixRanking>0</MatrixRanking></Field><Field><FieldName>csqr_q23</FieldName><FormName>coping_strategies_questionnaire_revised</FormName><FieldOrder>25</FieldOrder><ElementType>radio</ElementType><ElementLabel>23. I rely on my faith in God.</ElementLabel><ElementEnum><RawValue>0, Never do that \n 1, Very rarely do that \n 2, Rarely do that \n 3, Sometimes do that \n 4, Often do that \n 5, Usually do that \n 6, Always do that</RawValue><StructuredValue><Value value="0">Never do that</Value><Value value="1">Very rarely do that</Value><Value value="2">Rarely do that</Value><Value value="3">Sometimes do that</Value><Value value="4">Often do that</Value><Value value="5">Usually do that</Value><Value value="6">Always do that</Value></StructuredValue></ElementEnum><FieldReq>0</FieldReq><MatrixGroupName>pain_scale</MatrixGroupName><MatrixRanking>0</MatrixRanking></Field><Field><FieldName>csqr_q24</FieldName><FormName>coping_strategies_questionnaire_revised</FormName><FieldOrder>26</FieldOrder><ElementType>radio</ElementType><ElementLabel>24. I feel like I can't go on.</ElementLabel><ElementEnum><RawValue>0, Never do that \n 1, Very rarely do that \n 2, Rarely do that \n 3, Sometimes do that \n 4, Often do that \n 5, Usually do that \n 6, Always do that</RawValue><StructuredValue><Value value="0">Never do that</Value><Value value="1">Very rarely do that</Value><Value value="2">Rarely do that</Value><Value value="3">Sometimes do that</Value><Value value="4">Often do that</Value><Value value="5">Usually do that</Value><Value value="6">Always do that</Value></StructuredValue></ElementEnum><FieldReq>0</FieldReq><MatrixGroupName>pain_scale</MatrixGroupName><MatrixRanking>0</MatrixRanking></Field><Field><FieldName>csqr_q25</FieldName><FormName>coping_strategies_questionnaire_revised</FormName><FieldOrder>27</FieldOrder><ElementType>radio</ElementType><ElementLabel>25. I think of things I enjoy doing.</ElementLabel><ElementEnum><RawValue>0, Never do that \n 1, Very rarely do that \n 2, Rarely do that \n 3, Sometimes do that \n 4, Often do that \n 5, Usually do that \n 6, Always do that</RawValue><StructuredValue><Value value="0">Never do that</Value><Value value="1">Very rarely do that</Value><Value value="2">Rarely do that</Value><Value value="3">Sometimes do that</Value><Value value="4">Often do that</Value><Value value="5">Usually do that</Value><Value value="6">Always do that</Value></StructuredValue></ElementEnum><FieldReq>0</FieldReq><MatrixGroupName>pain_scale</MatrixGroupName><MatrixRanking>0</MatrixRanking></Field><Field><FieldName>csqr_q26</FieldName><FormName>coping_strategies_questionnaire_revised</FormName><FieldOrder>28</FieldOrder><ElementType>radio</ElementType><ElementLabel>26. I do something I enjoy, such as watching TV or listening to music.</ElementLabel><ElementEnum><RawValue>0, Never do that \n 1, Very rarely do that \n 2, Rarely do that \n 3, Sometimes do that \n 4, Often do that \n 5, Usually do that \n 6, Always do that</RawValue><StructuredValue><Value value="0">Never do that</Value><Value value="1">Very rarely do that</Value><Value value="2">Rarely do that</Value><Value value="3">Sometimes do that</Value><Value value="4">Often do that</Value><Value value="5">Usually do that</Value><Value value="6">Always do that</Value></StructuredValue></ElementEnum><FieldReq>0</FieldReq><MatrixGroupName>pain_scale</MatrixGroupName><MatrixRanking>0</MatrixRanking></Field><Field><FieldName>csqr_q27</FieldName><FormName>coping_strategies_questionnaire_revised</FormName><FieldOrder>29</FieldOrder><ElementType>radio</ElementType><ElementLabel>27. I pretend it's not a part of me.</ElementLabel><ElementEnum><RawValue>0, Never do that \n 1, Very rarely do that \n 2, Rarely do that \n 3, Sometimes do that \n 4, Often do that \n 5, Usually do that \n 6, Always do that</RawValue><StructuredValue><Value value="0">Never do that</Value><Value value="1">Very rarely do that</Value><Value value="2">Rarely do that</Value><Value value="3">Sometimes do that</Value><Value value="4">Often do that</Value><Value value="5">Usually do that</Value><Value value="6">Always do that</Value></StructuredValue></ElementEnum><FieldReq>0</FieldReq><MatrixGroupName>pain_scale</MatrixGroupName><MatrixRanking>0</MatrixRanking></Field></Metadata></SharedInstrument>
