<?xml version="1.0" encoding="UTF-8"?>
<SharedInstrument><Metadata type="crf"><Field><FieldName>cpaqr_1_sc</FieldName><FormName>chronic_pain_acceptance_questionnaire_revised_a963</FormName><FormMenuDescription>Chronic Pain Acceptance Questionnaire - Revised (CPAQ-R) scored</FormMenuDescription><FieldOrder>993</FieldOrder><ElementPreceedingHeader>CHRONIC PAIN ACCEPTANCE QUESTIONNAIRE (Revised)

Below you will find a list of statements. Please rate the truth of each statement as it applies to you. Use the following rating scale to make your choices. For instance, if you believe a statement is 'Always True,' you would choose 6 in the radio button next to that statement.</ElementPreceedingHeader><ElementType>radio</ElementType><ElementLabel>1. I am getting on with the business of living no matter what my level of pain is.</ElementLabel><ElementEnum><RawValue>0, 0 &lt;br/&gt;Never true \n 1, 1 &lt;br/&gt;Very rarely true \n 2, 2 &lt;br/&gt;Seldom True \n 3, 3 &lt;br/&gt;Sometimes true \n 4, 4 &lt;br/&gt;Often true \n 5, 5 &lt;br/&gt; Almost always true \n 6, 6 &lt;br/&gt; Always true</RawValue><StructuredValue><Value value="0">0 &lt;br/&gt;Never true</Value><Value value="1">1 &lt;br/&gt;Very rarely true</Value><Value value="2">2 &lt;br/&gt;Seldom True</Value><Value value="3">3 &lt;br/&gt;Sometimes true</Value><Value value="4">4 &lt;br/&gt;Often true</Value><Value value="5">5 &lt;br/&gt; Almost always true</Value><Value value="6">6 &lt;br/&gt; Always true</Value></StructuredValue></ElementEnum><FieldReq>0</FieldReq><MatrixGroupName>cpaqr_sc</MatrixGroupName><MatrixRanking>0</MatrixRanking></Field><Field><FieldName>cpaqr_2_sc</FieldName><FormName>chronic_pain_acceptance_questionnaire_revised_a963</FormName><FieldOrder>994</FieldOrder><ElementType>radio</ElementType><ElementLabel>2. My life is going well, even though I have chronic pain.</ElementLabel><ElementEnum><RawValue>0, 0 &lt;br/&gt;Never true \n 1, 1 &lt;br/&gt;Very rarely true \n 2, 2 &lt;br/&gt;Seldom True \n 3, 3 &lt;br/&gt;Sometimes true \n 4, 4 &lt;br/&gt;Often true \n 5, 5 &lt;br/&gt; Almost always true \n 6, 6 &lt;br/&gt; Always true</RawValue><StructuredValue><Value value="0">0 &lt;br/&gt;Never true</Value><Value value="1">1 &lt;br/&gt;Very rarely true</Value><Value value="2">2 &lt;br/&gt;Seldom True</Value><Value value="3">3 &lt;br/&gt;Sometimes true</Value><Value value="4">4 &lt;br/&gt;Often true</Value><Value value="5">5 &lt;br/&gt; Almost always true</Value><Value value="6">6 &lt;br/&gt; Always true</Value></StructuredValue></ElementEnum><FieldReq>0</FieldReq><MatrixGroupName>cpaqr_sc</MatrixGroupName><MatrixRanking>0</MatrixRanking></Field><Field><FieldName>cpaqr_3_sc</FieldName><FormName>chronic_pain_acceptance_questionnaire_revised_a963</FormName><FieldOrder>995</FieldOrder><ElementType>radio</ElementType><ElementLabel>3. It's OK to experience pain.</ElementLabel><ElementEnum><RawValue>0, 0 &lt;br/&gt;Never true \n 1, 1 &lt;br/&gt;Very rarely true \n 2, 2 &lt;br/&gt;Seldom True \n 3, 3 &lt;br/&gt;Sometimes true \n 4, 4 &lt;br/&gt;Often true \n 5, 5 &lt;br/&gt; Almost always true \n 6, 6 &lt;br/&gt; Always true</RawValue><StructuredValue><Value value="0">0 &lt;br/&gt;Never true</Value><Value value="1">1 &lt;br/&gt;Very rarely true</Value><Value value="2">2 &lt;br/&gt;Seldom True</Value><Value value="3">3 &lt;br/&gt;Sometimes true</Value><Value value="4">4 &lt;br/&gt;Often true</Value><Value value="5">5 &lt;br/&gt; Almost always true</Value><Value value="6">6 &lt;br/&gt; Always true</Value></StructuredValue></ElementEnum><FieldReq>0</FieldReq><MatrixGroupName>cpaqr_sc</MatrixGroupName><MatrixRanking>0</MatrixRanking></Field><Field><FieldName>cpaqr_4_sc</FieldName><FormName>chronic_pain_acceptance_questionnaire_revised_a963</FormName><FieldOrder>996</FieldOrder><ElementType>radio</ElementType><ElementLabel>4. I would gladly sacrifice important things in my life to control this pain better.</ElementLabel><ElementEnum><RawValue>0, 0 &lt;br/&gt;Never true \n 1, 1 &lt;br/&gt;Very rarely true \n 2, 2 &lt;br/&gt;Seldom True \n 3, 3 &lt;br/&gt;Sometimes true \n 4, 4 &lt;br/&gt;Often true \n 5, 5 &lt;br/&gt; Almost always true \n 6, 6 &lt;br/&gt; Always true</RawValue><StructuredValue><Value value="0">0 &lt;br/&gt;Never true</Value><Value value="1">1 &lt;br/&gt;Very rarely true</Value><Value value="2">2 &lt;br/&gt;Seldom True</Value><Value value="3">3 &lt;br/&gt;Sometimes true</Value><Value value="4">4 &lt;br/&gt;Often true</Value><Value value="5">5 &lt;br/&gt; Almost always true</Value><Value value="6">6 &lt;br/&gt; Always true</Value></StructuredValue></ElementEnum><FieldReq>0</FieldReq><MatrixGroupName>cpaqr_sc</MatrixGroupName><MatrixRanking>0</MatrixRanking></Field><Field><FieldName>cpaqr_5_sc</FieldName><FormName>chronic_pain_acceptance_questionnaire_revised_a963</FormName><FieldOrder>997</FieldOrder><ElementType>radio</ElementType><ElementLabel>5. It's not necessary for me to control my pain in order to handle my life well.</ElementLabel><ElementEnum><RawValue>0, 0 &lt;br/&gt;Never true \n 1, 1 &lt;br/&gt;Very rarely true \n 2, 2 &lt;br/&gt;Seldom True \n 3, 3 &lt;br/&gt;Sometimes true \n 4, 4 &lt;br/&gt;Often true \n 5, 5 &lt;br/&gt; Almost always true \n 6, 6 &lt;br/&gt; Always true</RawValue><StructuredValue><Value value="0">0 &lt;br/&gt;Never true</Value><Value value="1">1 &lt;br/&gt;Very rarely true</Value><Value value="2">2 &lt;br/&gt;Seldom True</Value><Value value="3">3 &lt;br/&gt;Sometimes true</Value><Value value="4">4 &lt;br/&gt;Often true</Value><Value value="5">5 &lt;br/&gt; Almost always true</Value><Value value="6">6 &lt;br/&gt; Always true</Value></StructuredValue></ElementEnum><FieldReq>0</FieldReq><MatrixGroupName>cpaqr_sc</MatrixGroupName><MatrixRanking>0</MatrixRanking></Field><Field><FieldName>cpaqr_6_sc</FieldName><FormName>chronic_pain_acceptance_questionnaire_revised_a963</FormName><FieldOrder>998</FieldOrder><ElementType>radio</ElementType><ElementLabel>6. Although things have changed, I am living a normal life despite my chronic pain.</ElementLabel><ElementEnum><RawValue>0, 0 &lt;br/&gt;Never true \n 1, 1 &lt;br/&gt;Very rarely true \n 2, 2 &lt;br/&gt;Seldom True \n 3, 3 &lt;br/&gt;Sometimes true \n 4, 4 &lt;br/&gt;Often true \n 5, 5 &lt;br/&gt; Almost always true \n 6, 6 &lt;br/&gt; Always true</RawValue><StructuredValue><Value value="0">0 &lt;br/&gt;Never true</Value><Value value="1">1 &lt;br/&gt;Very rarely true</Value><Value value="2">2 &lt;br/&gt;Seldom True</Value><Value value="3">3 &lt;br/&gt;Sometimes true</Value><Value value="4">4 &lt;br/&gt;Often true</Value><Value value="5">5 &lt;br/&gt; Almost always true</Value><Value value="6">6 &lt;br/&gt; Always true</Value></StructuredValue></ElementEnum><FieldReq>0</FieldReq><MatrixGroupName>cpaqr_sc</MatrixGroupName><MatrixRanking>0</MatrixRanking></Field><Field><FieldName>cpaqr_7_sc</FieldName><FormName>chronic_pain_acceptance_questionnaire_revised_a963</FormName><FieldOrder>999</FieldOrder><ElementType>radio</ElementType><ElementLabel>7. I need to concentrate on getting ride of my pain.</ElementLabel><ElementEnum><RawValue>0, 0 &lt;br/&gt;Never true \n 1, 1 &lt;br/&gt;Very rarely true \n 2, 2 &lt;br/&gt;Seldom True \n 3, 3 &lt;br/&gt;Sometimes true \n 4, 4 &lt;br/&gt;Often true \n 5, 5 &lt;br/&gt; Almost always true \n 6, 6 &lt;br/&gt; Always true</RawValue><StructuredValue><Value value="0">0 &lt;br/&gt;Never true</Value><Value value="1">1 &lt;br/&gt;Very rarely true</Value><Value value="2">2 &lt;br/&gt;Seldom True</Value><Value value="3">3 &lt;br/&gt;Sometimes true</Value><Value value="4">4 &lt;br/&gt;Often true</Value><Value value="5">5 &lt;br/&gt; Almost always true</Value><Value value="6">6 &lt;br/&gt; Always true</Value></StructuredValue></ElementEnum><FieldReq>0</FieldReq><MatrixGroupName>cpaqr_sc</MatrixGroupName><MatrixRanking>0</MatrixRanking></Field><Field><FieldName>cpaqr_8_sc</FieldName><FormName>chronic_pain_acceptance_questionnaire_revised_a963</FormName><FieldOrder>1000</FieldOrder><ElementType>radio</ElementType><ElementLabel>8. There are many activities I do when I feel pain.</ElementLabel><ElementEnum><RawValue>0, 0 &lt;br/&gt;Never true \n 1, 1 &lt;br/&gt;Very rarely true \n 2, 2 &lt;br/&gt;Seldom True \n 3, 3 &lt;br/&gt;Sometimes true \n 4, 4 &lt;br/&gt;Often true \n 5, 5 &lt;br/&gt; Almost always true \n 6, 6 &lt;br/&gt; Always true</RawValue><StructuredValue><Value value="0">0 &lt;br/&gt;Never true</Value><Value value="1">1 &lt;br/&gt;Very rarely true</Value><Value value="2">2 &lt;br/&gt;Seldom True</Value><Value value="3">3 &lt;br/&gt;Sometimes true</Value><Value value="4">4 &lt;br/&gt;Often true</Value><Value value="5">5 &lt;br/&gt; Almost always true</Value><Value value="6">6 &lt;br/&gt; Always true</Value></StructuredValue></ElementEnum><FieldReq>0</FieldReq><MatrixGroupName>cpaqr_sc</MatrixGroupName><MatrixRanking>0</MatrixRanking></Field><Field><FieldName>cpaqr_9_sc</FieldName><FormName>chronic_pain_acceptance_questionnaire_revised_a963</FormName><FieldOrder>1001</FieldOrder><ElementType>radio</ElementType><ElementLabel>9. I lead a full life even though I have chronic pain.</ElementLabel><ElementEnum><RawValue>0, 0 &lt;br/&gt;Never true \n 1, 1 &lt;br/&gt;Very rarely true \n 2, 2 &lt;br/&gt;Seldom True \n 3, 3 &lt;br/&gt;Sometimes true \n 4, 4 &lt;br/&gt;Often true \n 5, 5 &lt;br/&gt; Almost always true \n 6, 6 &lt;br/&gt; Always true</RawValue><StructuredValue><Value value="0">0 &lt;br/&gt;Never true</Value><Value value="1">1 &lt;br/&gt;Very rarely true</Value><Value value="2">2 &lt;br/&gt;Seldom True</Value><Value value="3">3 &lt;br/&gt;Sometimes true</Value><Value value="4">4 &lt;br/&gt;Often true</Value><Value value="5">5 &lt;br/&gt; Almost always true</Value><Value value="6">6 &lt;br/&gt; Always true</Value></StructuredValue></ElementEnum><FieldReq>0</FieldReq><MatrixGroupName>cpaqr_sc</MatrixGroupName><MatrixRanking>0</MatrixRanking></Field><Field><FieldName>cpaqr_10_sc</FieldName><FormName>chronic_pain_acceptance_questionnaire_revised_a963</FormName><FieldOrder>1002</FieldOrder><ElementType>radio</ElementType><ElementLabel>10. Controlling my pain is less important than any other goals in my life.</ElementLabel><ElementEnum><RawValue>0, 0 &lt;br/&gt;Never true \n 1, 1 &lt;br/&gt;Very rarely true \n 2, 2 &lt;br/&gt;Seldom True \n 3, 3 &lt;br/&gt;Sometimes true \n 4, 4 &lt;br/&gt;Often true \n 5, 5 &lt;br/&gt; Almost always true \n 6, 6 &lt;br/&gt; Always true</RawValue><StructuredValue><Value value="0">0 &lt;br/&gt;Never true</Value><Value value="1">1 &lt;br/&gt;Very rarely true</Value><Value value="2">2 &lt;br/&gt;Seldom True</Value><Value value="3">3 &lt;br/&gt;Sometimes true</Value><Value value="4">4 &lt;br/&gt;Often true</Value><Value value="5">5 &lt;br/&gt; Almost always true</Value><Value value="6">6 &lt;br/&gt; Always true</Value></StructuredValue></ElementEnum><FieldReq>0</FieldReq><MatrixGroupName>cpaqr_sc</MatrixGroupName><MatrixRanking>0</MatrixRanking></Field><Field><FieldName>cpaqr_11_sc</FieldName><FormName>chronic_pain_acceptance_questionnaire_revised_a963</FormName><FieldOrder>1003</FieldOrder><ElementType>radio</ElementType><ElementLabel>11. My thoughts and feelings about pain must change before I can take important steps in my life.</ElementLabel><ElementEnum><RawValue>0, 0 &lt;br/&gt;Never true \n 1, 1 &lt;br/&gt;Very rarely true \n 2, 2 &lt;br/&gt;Seldom True \n 3, 3 &lt;br/&gt;Sometimes true \n 4, 4 &lt;br/&gt;Often true \n 5, 5 &lt;br/&gt; Almost always true \n 6, 6 &lt;br/&gt; Always true</RawValue><StructuredValue><Value value="0">0 &lt;br/&gt;Never true</Value><Value value="1">1 &lt;br/&gt;Very rarely true</Value><Value value="2">2 &lt;br/&gt;Seldom True</Value><Value value="3">3 &lt;br/&gt;Sometimes true</Value><Value value="4">4 &lt;br/&gt;Often true</Value><Value value="5">5 &lt;br/&gt; Almost always true</Value><Value value="6">6 &lt;br/&gt; Always true</Value></StructuredValue></ElementEnum><FieldReq>0</FieldReq><MatrixGroupName>cpaqr_sc</MatrixGroupName><MatrixRanking>0</MatrixRanking></Field><Field><FieldName>cpaqr_12_sc</FieldName><FormName>chronic_pain_acceptance_questionnaire_revised_a963</FormName><FieldOrder>1004</FieldOrder><ElementType>radio</ElementType><ElementLabel>12. Despite the pain, I am now sticking to a certain course in my life.</ElementLabel><ElementEnum><RawValue>0, 0 &lt;br/&gt;Never true \n 1, 1 &lt;br/&gt;Very rarely true \n 2, 2 &lt;br/&gt;Seldom True \n 3, 3 &lt;br/&gt;Sometimes true \n 4, 4 &lt;br/&gt;Often true \n 5, 5 &lt;br/&gt; Almost always true \n 6, 6 &lt;br/&gt; Always true</RawValue><StructuredValue><Value value="0">0 &lt;br/&gt;Never true</Value><Value value="1">1 &lt;br/&gt;Very rarely true</Value><Value value="2">2 &lt;br/&gt;Seldom True</Value><Value value="3">3 &lt;br/&gt;Sometimes true</Value><Value value="4">4 &lt;br/&gt;Often true</Value><Value value="5">5 &lt;br/&gt; Almost always true</Value><Value value="6">6 &lt;br/&gt; Always true</Value></StructuredValue></ElementEnum><FieldReq>0</FieldReq><MatrixGroupName>cpaqr_sc</MatrixGroupName><MatrixRanking>0</MatrixRanking></Field><Field><FieldName>cpaqr_13_sc</FieldName><FormName>chronic_pain_acceptance_questionnaire_revised_a963</FormName><FieldOrder>1005</FieldOrder><ElementType>radio</ElementType><ElementLabel>13. Keeping my pain level under control takes first priority whenever I'm doing something.</ElementLabel><ElementEnum><RawValue>0, 0 &lt;br/&gt;Never true \n 1, 1 &lt;br/&gt;Very rarely true \n 2, 2 &lt;br/&gt;Seldom True \n 3, 3 &lt;br/&gt;Sometimes true \n 4, 4 &lt;br/&gt;Often true \n 5, 5 &lt;br/&gt; Almost always true \n 6, 6 &lt;br/&gt; Always true</RawValue><StructuredValue><Value value="0">0 &lt;br/&gt;Never true</Value><Value value="1">1 &lt;br/&gt;Very rarely true</Value><Value value="2">2 &lt;br/&gt;Seldom True</Value><Value value="3">3 &lt;br/&gt;Sometimes true</Value><Value value="4">4 &lt;br/&gt;Often true</Value><Value value="5">5 &lt;br/&gt; Almost always true</Value><Value value="6">6 &lt;br/&gt; Always true</Value></StructuredValue></ElementEnum><FieldReq>0</FieldReq><MatrixGroupName>cpaqr_sc</MatrixGroupName><MatrixRanking>0</MatrixRanking></Field><Field><FieldName>cpaqr_14_sc</FieldName><FormName>chronic_pain_acceptance_questionnaire_revised_a963</FormName><FieldOrder>1006</FieldOrder><ElementType>radio</ElementType><ElementLabel>14. Before I can make any serious plans, I have to get some control over my pain.</ElementLabel><ElementEnum><RawValue>0, 0 &lt;br/&gt;Never true \n 1, 1 &lt;br/&gt;Very rarely true \n 2, 2 &lt;br/&gt;Seldom True \n 3, 3 &lt;br/&gt;Sometimes true \n 4, 4 &lt;br/&gt;Often true \n 5, 5 &lt;br/&gt; Almost always true \n 6, 6 &lt;br/&gt; Always true</RawValue><StructuredValue><Value value="0">0 &lt;br/&gt;Never true</Value><Value value="1">1 &lt;br/&gt;Very rarely true</Value><Value value="2">2 &lt;br/&gt;Seldom True</Value><Value value="3">3 &lt;br/&gt;Sometimes true</Value><Value value="4">4 &lt;br/&gt;Often true</Value><Value value="5">5 &lt;br/&gt; Almost always true</Value><Value value="6">6 &lt;br/&gt; Always true</Value></StructuredValue></ElementEnum><FieldReq>0</FieldReq><MatrixGroupName>cpaqr_sc</MatrixGroupName><MatrixRanking>0</MatrixRanking></Field><Field><FieldName>cpaqr_15_sc</FieldName><FormName>chronic_pain_acceptance_questionnaire_revised_a963</FormName><FieldOrder>1007</FieldOrder><ElementType>radio</ElementType><ElementLabel>15. When my pain increases, I can still take care of my responsibilities.</ElementLabel><ElementEnum><RawValue>0, 0 &lt;br/&gt;Never true \n 1, 1 &lt;br/&gt;Very rarely true \n 2, 2 &lt;br/&gt;Seldom True \n 3, 3 &lt;br/&gt;Sometimes true \n 4, 4 &lt;br/&gt;Often true \n 5, 5 &lt;br/&gt; Almost always true \n 6, 6 &lt;br/&gt; Always true</RawValue><StructuredValue><Value value="0">0 &lt;br/&gt;Never true</Value><Value value="1">1 &lt;br/&gt;Very rarely true</Value><Value value="2">2 &lt;br/&gt;Seldom True</Value><Value value="3">3 &lt;br/&gt;Sometimes true</Value><Value value="4">4 &lt;br/&gt;Often true</Value><Value value="5">5 &lt;br/&gt; Almost always true</Value><Value value="6">6 &lt;br/&gt; Always true</Value></StructuredValue></ElementEnum><FieldReq>0</FieldReq><MatrixGroupName>cpaqr_sc</MatrixGroupName><MatrixRanking>0</MatrixRanking></Field><Field><FieldName>cpaqr_16_sc</FieldName><FormName>chronic_pain_acceptance_questionnaire_revised_a963</FormName><FieldOrder>1008</FieldOrder><ElementType>radio</ElementType><ElementLabel>16. I will have better control over my life if I can control my negative thoughts about pain.</ElementLabel><ElementEnum><RawValue>0, 0 &lt;br/&gt;Never true \n 1, 1 &lt;br/&gt;Very rarely true \n 2, 2 &lt;br/&gt;Seldom True \n 3, 3 &lt;br/&gt;Sometimes true \n 4, 4 &lt;br/&gt;Often true \n 5, 5 &lt;br/&gt; Almost always true \n 6, 6 &lt;br/&gt; Always true</RawValue><StructuredValue><Value value="0">0 &lt;br/&gt;Never true</Value><Value value="1">1 &lt;br/&gt;Very rarely true</Value><Value value="2">2 &lt;br/&gt;Seldom True</Value><Value value="3">3 &lt;br/&gt;Sometimes true</Value><Value value="4">4 &lt;br/&gt;Often true</Value><Value value="5">5 &lt;br/&gt; Almost always true</Value><Value value="6">6 &lt;br/&gt; Always true</Value></StructuredValue></ElementEnum><FieldReq>0</FieldReq><MatrixGroupName>cpaqr_sc</MatrixGroupName><MatrixRanking>0</MatrixRanking></Field><Field><FieldName>cpaqr_17_sc</FieldName><FormName>chronic_pain_acceptance_questionnaire_revised_a963</FormName><FieldOrder>1009</FieldOrder><ElementType>radio</ElementType><ElementLabel>17. I avoid putting myself in situations where my pain might increase.</ElementLabel><ElementEnum><RawValue>0, 0 &lt;br/&gt;Never true \n 1, 1 &lt;br/&gt;Very rarely true \n 2, 2 &lt;br/&gt;Seldom True \n 3, 3 &lt;br/&gt;Sometimes true \n 4, 4 &lt;br/&gt;Often true \n 5, 5 &lt;br/&gt; Almost always true \n 6, 6 &lt;br/&gt; Always true</RawValue><StructuredValue><Value value="0">0 &lt;br/&gt;Never true</Value><Value value="1">1 &lt;br/&gt;Very rarely true</Value><Value value="2">2 &lt;br/&gt;Seldom True</Value><Value value="3">3 &lt;br/&gt;Sometimes true</Value><Value value="4">4 &lt;br/&gt;Often true</Value><Value value="5">5 &lt;br/&gt; Almost always true</Value><Value value="6">6 &lt;br/&gt; Always true</Value></StructuredValue></ElementEnum><FieldReq>0</FieldReq><MatrixGroupName>cpaqr_sc</MatrixGroupName><MatrixRanking>0</MatrixRanking></Field><Field><FieldName>cpaqr_18_sc</FieldName><FormName>chronic_pain_acceptance_questionnaire_revised_a963</FormName><FieldOrder>1010</FieldOrder><ElementType>radio</ElementType><ElementLabel>18. My worries and fears about what pain will do to me are true.</ElementLabel><ElementEnum><RawValue>0, 0 &lt;br/&gt;Never true \n 1, 1 &lt;br/&gt;Very rarely true \n 2, 2 &lt;br/&gt;Seldom True \n 3, 3 &lt;br/&gt;Sometimes true \n 4, 4 &lt;br/&gt;Often true \n 5, 5 &lt;br/&gt; Almost always true \n 6, 6 &lt;br/&gt; Always true</RawValue><StructuredValue><Value value="0">0 &lt;br/&gt;Never true</Value><Value value="1">1 &lt;br/&gt;Very rarely true</Value><Value value="2">2 &lt;br/&gt;Seldom True</Value><Value value="3">3 &lt;br/&gt;Sometimes true</Value><Value value="4">4 &lt;br/&gt;Often true</Value><Value value="5">5 &lt;br/&gt; Almost always true</Value><Value value="6">6 &lt;br/&gt; Always true</Value></StructuredValue></ElementEnum><FieldReq>0</FieldReq><MatrixGroupName>cpaqr_sc</MatrixGroupName><MatrixRanking>0</MatrixRanking></Field><Field><FieldName>cpaqr_19_sc</FieldName><FormName>chronic_pain_acceptance_questionnaire_revised_a963</FormName><FieldOrder>1011</FieldOrder><ElementType>radio</ElementType><ElementLabel>19. It's a great relief to realize that I don't have to change my pain to get on with life</ElementLabel><ElementEnum><RawValue>0, 0 &lt;br/&gt;Never true \n 1, 1 &lt;br/&gt;Very rarely true \n 2, 2 &lt;br/&gt;Seldom True \n 3, 3 &lt;br/&gt;Sometimes true \n 4, 4 &lt;br/&gt;Often true \n 5, 5 &lt;br/&gt; Almost always true \n 6, 6 &lt;br/&gt; Always true</RawValue><StructuredValue><Value value="0">0 &lt;br/&gt;Never true</Value><Value value="1">1 &lt;br/&gt;Very rarely true</Value><Value value="2">2 &lt;br/&gt;Seldom True</Value><Value value="3">3 &lt;br/&gt;Sometimes true</Value><Value value="4">4 &lt;br/&gt;Often true</Value><Value value="5">5 &lt;br/&gt; Almost always true</Value><Value value="6">6 &lt;br/&gt; Always true</Value></StructuredValue></ElementEnum><FieldReq>0</FieldReq><MatrixGroupName>cpaqr_sc</MatrixGroupName><MatrixRanking>0</MatrixRanking></Field><Field><FieldName>cpaqr_20_sc</FieldName><FormName>chronic_pain_acceptance_questionnaire_revised_a963</FormName><FieldOrder>1012</FieldOrder><ElementType>radio</ElementType><ElementLabel>20. I have to struggle to do things when I have pain</ElementLabel><ElementEnum><RawValue>0, 0 &lt;br/&gt;Never true \n 1, 1 &lt;br/&gt;Very rarely true \n 2, 2 &lt;br/&gt;Seldom True \n 3, 3 &lt;br/&gt;Sometimes true \n 4, 4 &lt;br/&gt;Often true \n 5, 5 &lt;br/&gt; Almost always true \n 6, 6 &lt;br/&gt; Always true</RawValue><StructuredValue><Value value="0">0 &lt;br/&gt;Never true</Value><Value value="1">1 &lt;br/&gt;Very rarely true</Value><Value value="2">2 &lt;br/&gt;Seldom True</Value><Value value="3">3 &lt;br/&gt;Sometimes true</Value><Value value="4">4 &lt;br/&gt;Often true</Value><Value value="5">5 &lt;br/&gt; Almost always true</Value><Value value="6">6 &lt;br/&gt; Always true</Value></StructuredValue></ElementEnum><FieldReq>0</FieldReq><MatrixGroupName>cpaqr_sc</MatrixGroupName><MatrixRanking>0</MatrixRanking></Field><Field><FieldName>activity_engagement_score</FieldName><FormName>chronic_pain_acceptance_questionnaire_revised_a963</FormName><FieldOrder>1013</FieldOrder><ElementType>calc</ElementType><ElementLabel>Activity engagement score</ElementLabel><ElementEnum><RawValue>sum([cpaqr_1_sc],[cpaqr_2_sc], [cpaqr_3_sc], [cpaqr_5_sc], [cpaqr_6_sc],[cpaqr_8_sc],[cpaqr_9_sc],[cpaqr_10_sc],[cpaqr_12_sc],[cpaqr_15_sc],[cpaqr_19_sc])</RawValue><StructuredValue><Value value="sum([cpaqr_1_sc]">[cpaqr_2_sc]</Value></StructuredValue></ElementEnum><FieldReq>0</FieldReq><MatrixRanking>0</MatrixRanking></Field><Field><FieldName>pain_willingness_score</FieldName><FormName>chronic_pain_acceptance_questionnaire_revised_a963</FormName><FieldOrder>1014</FieldOrder><ElementType>calc</ElementType><ElementLabel>Pain willingness score</ElementLabel><ElementEnum><RawValue>sum([cpaqr_4_sc],[cpaqr_7_sc], [cpaqr_11_sc], [cpaqr_13_sc], [cpaqr_14_sc],[cpaqr_16_sc],[cpaqr_17_sc],[cpaqr_18_sc],[cpaqr_20_sc])</RawValue><StructuredValue><Value value="sum([cpaqr_4_sc]">[cpaqr_7_sc]</Value></StructuredValue></ElementEnum><FieldReq>0</FieldReq><MatrixRanking>0</MatrixRanking></Field><Field><FieldName>totalscore_cpaqr</FieldName><FormName>chronic_pain_acceptance_questionnaire_revised_a963</FormName><FieldOrder>1015</FieldOrder><ElementType>calc</ElementType><ElementLabel>Total score</ElementLabel><ElementEnum><RawValue>sum([cpaqr_1_sc],[cpaqr_2_sc], [cpaqr_3_sc], [cpaqr_5_sc], [cpaqr_6_sc],[cpaqr_8_sc],[cpaqr_9_sc],[cpaqr_10_sc],[cpaqr_12_sc],[cpaqr_15_sc],[cpaqr_19_sc], [cpaqr_4_sc],[cpaqr_7_sc], [cpaqr_11_sc], [cpaqr_13_sc], [cpaqr_14_sc],[cpaqr_16_sc],[cpaqr_17_sc],[cpaqr_18_sc],[cpaqr_20_sc])</RawValue><StructuredValue><Value value="sum([cpaqr_1_sc]">[cpaqr_2_sc]</Value></StructuredValue></ElementEnum><FieldReq>0</FieldReq><MatrixRanking>0</MatrixRanking></Field></Metadata></SharedInstrument>
